{
  "$schema": "../gen/schemas/desktop-schema.json",
  "identifier": "default",
  "description": "Capability for the main window",
  "windows": ["overlay", "settings"],
  "permissions": [
    "core:default",
    "core:window:allow-set-shadow",
    "core:window:allow-set-ignore-cursor-events",
    "core:window:allow-hide",
    "core:window:allow-set-size",
    "core:window:allow-set-position",
    "dialog:default",
    "fs:default",
    "global-shortcut:allow-register",
    "global-shortcut:allow-unregister",
    "global-shortcut:allow-unregister-all",
    "notification:default"
  ]
}
